helper/reg_file.v
module reg_file(
    input clk, rst,
    input [2:0] rd_addr1,
    input [2:0] rd_addr2,
    input [2:0] wr_addr,
    input [15:0] wr_data,
    input wr_en, pc_wr,
    input [15:0] pc_next,
    output [15:0] rd_data1,
    output [15:0] rd_data2,
    output [15:0] pc
);

    reg [15:0] regFile [7:0];

    assign rd_data1 = regFile[rd_addr1];
    assign rd_data2 = regFile[rd_addr2];
    assign pc = regFile[3'b111];

    integer i;

    always @(posedge clk) begin
        if(rst == 1'b1) begin
            for (i=0; i<8; i=i+1)
                regFile[i] = 16'd0;
        end else begin
            if(wr_en == 1'b1) begin
                regFile[wr_addr] <= wr_data;
            end
            if(pc_wr == 1'b1) begin
                regFile[3'b111] <= pc_next;
            end
        end
    end

endmodule

units/hazard_detection_unit.v
module hazard_detection_unit (
    input rst,
    input [3:0] op_decode, op_regread,
    input [2:0] src1_decode, src2_decode, dest_regread,
    output reg should_stall
);
    wire src1_depend, src2_depend;
    assign src1_depend = src1_decode^dest_regread;
    assign src2_depend = src2_decode^dest_regread;

    always @(*) begin
        if(rst == 1'b1) begin
            should_stall <= 1'b0;
        end else begin
            case (op_regread)
                0100:
                    should_stall <= (src1_depend | src2_depend);
                default: 
                    should_stall <= 1'b0;
            endcase
        end
    end

endmodule

helper/alu.v
module alu(
    input [1:0] sel,
    input [15:0] arg1, arg2,
    output [15:0] result,
    output carry_out, zero_out
);

    reg [15:0] alu_result;
    assign result = alu_result;
    wire [16:0] tmp = {1'b0, arg1} + {1'b0, arg2};
    assign carry_out = tmp[16];

    assign zero_out = (alu_result == 16'd0) ? 1'b1 : 1'b0;
    
    always @(*) begin
        case (sel)
            3'b00:
                alu_result = (arg1 + arg2);
            3'b01:
                alu_result <= !(arg1 && arg2);
            default: 
                alu_result = (arg1 + arg2);
        endcase

        // if(alu_result == 16'd0) 
        //     zero_out = 1'b1;
        // else
        //     zero_out = 1'b0;
         
    end

endmodule

stages/execute.v
module execute (
    input [40:0] instr_in,
    input C_in, Z_in,

    output C_out, Z_out
);
    reg [1:0] alu_op;
    reg [15:0] src1, src2, alu_result;
    alu alu_instance(.sel(alu_op), .arg1(), .arg2(), .result(), .carry_out(C_out),  .zero_out(Z_out));

    always @(*) begin
        case (instr[40:37])
            0001:
                alu_op <= 2'b00;
                 
            default: 
        endcase
    end

endmodule

helper/fifo.v
module fifo (
    input en, clk, rst,
    input [40:0] data_in,
    output reg [40:0] data_out
);

    always @(posedge clk) begin
        if(rst == 1'b1)
            data_out <= 41'd0;
        else begin
            if(en == 1'b1)
                data_out <= data_in;
            else
                data_out <= 41'd0; 
        end
    end
    
endmodule

stages/register_read.v
module register_read (
    input [40:0] instr_in,
    output [40:0] instr_out,
    input [15:0] rd_data1, rd_data2,
    output [2:0] rd_addr1, rd_addr2
);

    always @(*) begin
        case (instr_in[40:37])
            0001:
                rd_addr1 <= instr_in[36:34];
                rd_addr2 <= instr_in[33:31];
                instr_out <= {instr_in[40:37], rd_data1, rd_data2, instr_in[30:26]};
            0000:
                rd_addr1 <= instr_in[36:34];
                instr_out <= {instr_in[40:37], rd_data1, instr_in[30:15], instr_in[33:31], 2'd0};
            0010:
                rd_addr1 <= instr_in[36:34];
                rd_addr2 <= instr_in[33:31];
                instr_out <= {instr_in[40:37], rd_data1, rd_data2, instr_in[30:26]};
            default:
                instr_out <= 41'd0;
        endcase
    end

endmodule

stages/decode.v
module decode (
    input rst,
    input [40:0] instr_in,
    input should_stall,
    output reg [40:0] instr_out,
    output reg [2:0] hdu_src1, hdu_src2,
    output reg [3:0] temp
);

    always @(*) begin
        temp <= instr_in[40:37];
        case (instr_in[40:37])
            0010: begin
                instr_out <= {instr_in[40:28], instr_in[26], instr_in[25], 26'd0};
                hdu_src1 <= instr_in[36:34];
                hdu_src1 <= instr_in[33:31];
            end
            // 0001: begin
            //     instr_out <= {instr_in[40:28], instr_in[26], instr_in[25], 26'd0};
            //     hdu_src1 <= instr_in[36:34];
            //     hdu_src2 <= instr_in[33:31];
            // end
            // 0000: begin
            //     instr_out <= {instr_in[40: 31], 10'd0, instr_in[30: 25], 15'd0};
            //     hdu_src1 <= instr_in[36:34];
            // end
            // 0011:
            //     instr_out <= {instr_in[40:34], 7'd0, instr_in[8:0], 18'd0};
            // 0100:
            //     instr_out <= {instr_in[40:31], 10'd0, instr_in[30:25], 15'd0};
            // 0101:
            //     instr_out <= {instr_in[40:31], 10'd0, instr_in[30:25], 15'd0};
            // 1100:
            //     instr_out <= {instr_in[40:34], instr_in[32:25], 26'd0};
            // 1101:
            //     instr_out <= {instr_in[40:34], instr_in[32:25], 26'd0};
            // 1110:
            //     instr_out <= {instr_in[40:34], 34'd0};
            // 1111:
            //     instr_out <= {instr_in[40:34], 34'd0};
            // 1000:
            //     instr_out <= {instr_in[40:31], 10'd0, instr_in[30:25], 15'd0};
            // 1001:
            //     instr_out <= {instr_in[40:34], 7'd0, instr_in[8:0], 18'd0};
            // 1010:
            //     instr_out <= {instr_in[40:31], 31'd0};
            // 1011:
            //     instr_out <= {instr_in[40:34], 7'd0, instr_in[8:0], 18'd0};
            default:
                instr_out <= 41'd0;
        endcase
    end

endmodule

helper/rom.v
module rom(
    input [15:0] pc,
    output [15:0] instr
);

    reg [15:0] romFile [2**15:0];

    assign instr = romFile[pc];

endmodule

stages/fetch.v
module fetch (
    input [15:0] pc,
    output reg [40:0] instruction,
    output [15:0] npc
);

    wire [15:0] temp_instr;
    rom rom_instance (.pc(pc), .instr(temp_instr) );

    assign npc = pc + 1;

    always @(*) begin
        instruction <= {temp_instr, 25'd0};
    end

endmodule

processor.v
module processor (
    input clk, rst
);

    reg fetch_en, decode_en, reg_read_en, execute_en, memory_access_en, write_back_en;
    wire [15:0] pc_in_fetch, npc_from_fetch;
    wire [40:0] fetch_decode_in, fetch_decode_out;
    wire [40:0] decode_regread_in, decode_regread_out;
    wire [40:0] regread_exe_in, regread_exe_out;
    wire [40:0] exe_memaccess_in, exe_memaccess_out;
    wire [40:0] memaccess_wb_in, memaccess_wb_out;

    wire [2:0] decode_hdu_src1, decode_hdu_src2, regread_hdu_dest;
    wire should_decode_stall;

    wire [2:0] reg_file_addr1, reg_file_addr2;
    wire [15:0] reg_file_data1, reg_file_data2;


    fetch fetch_instance (.pc(pc_in_fetch), .instruction(fetch_decode_in), .npc(npc_from_fetch));

    fifo fetch_decode_fifo(.en(~should_decode_stall), .clk(clk), .data_in(fetch_decode_in), .data_out(fetch_decode_out));

    decode decode_instance(.instr_in(fetch_decode_out), .instr_out(decode_regread_in), .hdu_src1(decode_hdu_src1), .hdu_src2(decode_hdu_src2));

    fifo decode_regread_fifo(.en(~should_decode_stall), .clk(clk), .data_in(decode_regread_in), .data_out(decode_regread_out));

    register_read regread_instance(.instr_in(decode_regread_out), .instr_out(regread_exe_in),
        .rd_data1(reg_file_data1),.rd_data2(reg_file_data2),
        .rd_addr1(reg_file_addr1), .rd_addr2(reg_file_addr2));

    fifo regread_exe_fifo(.en(reg_read_en), .clk(clk), .data_in(regread_exe_in), .data_out(regread_exe_out));

    execute execute_instance();

    hazard_detection_unit hdu_instance(.op_decode(fetch_decode_out[25:22]), .op_regread(decode_regread_out[25:22]), 
        .src1_decode(decode_hdu_src1), .src2_decode(decode_hdu_src2), .dest_regread(regread_hdu_dest), .should_stall(should_decode_stall));

    reg_file reg_file_instance (.clk(clk), .rst(rst), .wr_en(), .pc_wr(~should_decode_stall),
        .rd_addr1(reg_file_addr1), .rd_addr2(reg_file_addr2),
        .wr_addr(), .wr_data(), .pc_next(npc_from_fetch), 
        .rd_data1(reg_file_data1), .rd_data2(reg_file_data2), .pc(pc_in_fetch));

    always @(clk, rst) begin
        
    end
    
endmodule

testbench.v
module testbench ();
    
    reg clk, rst;
    always #25 clk = ~clk;

    processor processor_instance(.clk(clk), .rst(rst));

    initial begin
        $dumpfile("proc.vcd");
        $dumpvars(0, testbench);

        #0 clk = 1'b0; rst = 1'b1;
        #30 rst = 1'b0;

        #500 $finish;
    end

endmodule

proc.vcd
$date
	Thu May 20 16:39:32 2021
$end
$version
	Icarus Verilog
$end
$timescale
	1s
$end
$scope module testbench $end
$var reg 1 ! clk $end
$var reg 1 " rst $end
$scope module processor_instance $end
$var wire 1 ! clk $end
$var wire 16 # pc_in_fetch [15:0] $end
$var wire 3 $ regread_hdu_dest [2:0] $end
$var wire 1 " rst $end
$var wire 1 % should_decode_stall $end
$var wire 41 & regread_exe_out [40:0] $end
$var wire 41 ' regread_exe_in [40:0] $end
$var wire 16 ( reg_file_data2 [15:0] $end
$var wire 16 ) reg_file_data1 [15:0] $end
$var wire 3 * reg_file_addr2 [2:0] $end
$var wire 3 + reg_file_addr1 [2:0] $end
$var wire 16 , npc_from_fetch [15:0] $end
$var wire 41 - fetch_decode_out [40:0] $end
$var wire 41 . fetch_decode_in [40:0] $end
$var wire 41 / decode_regread_out [40:0] $end
$var wire 41 0 decode_regread_in [40:0] $end
$var wire 3 1 decode_hdu_src2 [2:0] $end
$var wire 3 2 decode_hdu_src1 [2:0] $end
$var reg 1 3 reg_read_en $end
$scope module decode_instance $end
$var wire 1 4 rst $end
$var wire 1 5 should_stall $end
$var wire 41 6 instr_in [40:0] $end
$var reg 3 7 hdu_src1 [2:0] $end
$var reg 3 8 hdu_src2 [2:0] $end
$var reg 41 9 instr_out [40:0] $end
$var reg 4 : temp [3:0] $end
$upscope $end
$scope module decode_regread_fifo $end
$var wire 1 ! clk $end
$var wire 41 ; data_in [40:0] $end
$var wire 1 < en $end
$var wire 1 = rst $end
$var reg 41 > data_out [40:0] $end
$upscope $end
$scope module execute_instance $end
$var wire 1 ? C_in $end
$var wire 1 @ Z_in $end
$var wire 41 A instr_in [40:0] $end
$var wire 1 B Z_out $end
$var wire 1 C C_out $end
$var reg 2 D alu_op [1:0] $end
$scope module alu_instance $end
$var wire 16 E arg1 [15:0] $end
$var wire 16 F arg2 [15:0] $end
$var wire 16 G result [15:0] $end
$var wire 2 H sel [1:0] $end
$var wire 1 B zero_out $end
$var wire 17 I tmp [16:0] $end
$var wire 1 C carry_out $end
$var reg 16 J alu_result [15:0] $end
$upscope $end
$upscope $end
$scope module fetch_decode_fifo $end
$var wire 1 ! clk $end
$var wire 1 K en $end
$var wire 1 L rst $end
$var wire 41 M data_in [40:0] $end
$var reg 41 N data_out [40:0] $end
$upscope $end
$scope module fetch_instance $end
$var wire 16 O pc [15:0] $end
$var wire 16 P temp_instr [15:0] $end
$var wire 16 Q npc [15:0] $end
$var reg 41 R instruction [40:0] $end
$scope module rom_instance $end
$var wire 16 S instr [15:0] $end
$var wire 16 T pc [15:0] $end
$upscope $end
$upscope $end
$scope module hdu_instance $end
$var wire 3 U dest_regread [2:0] $end
$var wire 4 V op_decode [3:0] $end
$var wire 4 W op_regread [3:0] $end
$var wire 1 X rst $end
$var wire 3 Y src1_decode [2:0] $end
$var wire 3 Z src2_decode [2:0] $end
$var wire 1 [ src2_depend $end
$var wire 1 \ src1_depend $end
$var reg 1 % should_stall $end
$upscope $end
$scope module reg_file_instance $end
$var wire 1 ! clk $end
$var wire 16 ] pc [15:0] $end
$var wire 16 ^ pc_next [15:0] $end
$var wire 1 _ pc_wr $end
$var wire 16 ` rd_data1 [15:0] $end
$var wire 16 a rd_data2 [15:0] $end
$var wire 1 " rst $end
$var wire 3 b wr_addr [2:0] $end
$var wire 16 c wr_data [15:0] $end
$var wire 1 d wr_en $end
$var wire 3 e rd_addr2 [2:0] $end
$var wire 3 f rd_addr1 [2:0] $end
$var integer 32 g i [31:0] $end
$upscope $end
$scope module regread_exe_fifo $end
$var wire 1 ! clk $end
$var wire 1 3 en $end
$var wire 1 h rst $end
$var wire 41 i data_in [40:0] $end
$var reg 41 j data_out [40:0] $end
$upscope $end
$scope module regread_instance $end
$var wire 41 k instr_in [40:0] $end
$var wire 16 l rd_data1 [15:0] $end
$var wire 16 m rd_data2 [15:0] $end
$var reg 41 n instr_out [40:0] $end
$var reg 3 o rd_addr1 [2:0] $end
$var reg 3 p rd_addr2 [2:0] $end
$upscope $end
$upscope $end
$upscope $end
$enddefinitions $end
#0
$dumpvars
bx p
bx o
bx n
bx m
bx l
bx k
bx j
bx i
zh
bx g
bx f
bx e
zd
bz c
bz b
bx a
bx `
1_
bx ^
bx ]
x\
x[
bx Z
bx Y
zX
bx W
bx V
bz U
bx T
bx S
bx R
bx Q
bx P
bx O
bx N
bx M
zL
1K
bx J
bx I
b0 H
bx G
bz F
bz E
b0 D
xC
xB
bz A
z@
z?
bx >
z=
1<
bx ;
bx :
bx 9
bx 8
bx 7
bx 6
z5
z4
x3
bx 2
bx 1
bx 0
bx /
bx .
bx -
bx ,
bx +
bx *
bx )
bx (
bx '
bx &
0%
bz $
bx #
1"
0!
$end
#25
b10010100110000000000000000000000000000 .
b10010100110000000000000000000000000000 M
b10010100110000000000000000000000000000 R
b0 &
b0 j
b1 ,
b1 Q
b1 ^
b1001010011000 P
b1001010011000 S
b0 #
b0 O
b0 T
b0 ]
b1000 g
1!
#30
0"
#50
0!
#75
b10010100110100000000000000000000000000 .
b10010100110100000000000000000000000000 M
b10010100110100000000000000000000000000 R
b0 0
b0 9
b0 ;
b1 :
b0 V
b10 ,
b10 Q
b10 ^
b1001010011010 P
b1001010011010 S
b1 #
b1 O
b1 T
b1 ]
b10010100110000000000000000000000000000 -
b10010100110000000000000000000000000000 6
b10010100110000000000000000000000000000 N
1!
#100
0!
#125
b0 '
b0 i
b0 n
b0 )
b0 `
b0 l
b0 +
b0 f
b0 o
b10010100110010000000000000000000000000 .
b10010100110010000000000000000000000000 M
b10010100110010000000000000000000000000 R
b0 W
b10010100110100000000000000000000000000 -
b10010100110100000000000000000000000000 6
b10010100110100000000000000000000000000 N
b0 /
b0 >
b0 k
b11 ,
b11 Q
b11 ^
b1001010011001 P
b1001010011001 S
b10 #
b10 O
b10 T
b10 ]
1!
#150
0!
#175
b10010100110110000000000000000000000000 .
b10010100110110000000000000000000000000 M
b10010100110110000000000000000000000000 R
b1000 V
b100 ,
b100 Q
b100 ^
b1001010011011 P
b1001010011011 S
b11 #
b11 O
b11 T
b11 ]
b10010100110010000000000000000000000000 -
b10010100110010000000000000000000000000 6
b10010100110010000000000000000000000000 N
1!
#200
0!
#225
b11001001010000000000000000000000000 .
b11001001010000000000000000000000000 M
b11001001010000000000000000000000000 R
b10010100110110000000000000000000000000 -
b10010100110110000000000000000000000000 6
b10010100110110000000000000000000000000 N
b101 ,
b101 Q
b101 ^
b1100100101 P
b1100100101 S
b100 #
b100 O
b100 T
b100 ]
1!
#250
0!
#275
b100010100110000000000000000000000000000 .
b100010100110000000000000000000000000000 M
b100010100110000000000000000000000000000 R
b0 :
b110 ,
b110 Q
b110 ^
b10001010011000 P
b10001010011000 S
b101 #
b101 O
b101 T
b101 ]
b11001001010000000000000000000000000 -
b11001001010000000000000000000000000 6
b11001001010000000000000000000000000 N
1!
#300
0!
#325
b10 :
b100010100110100000000000000000000000000 .
b100010100110100000000000000000000000000 M
b100010100110100000000000000000000000000 R
b0 V
b100010100110000000000000000000000000000 -
b100010100110000000000000000000000000000 6
b100010100110000000000000000000000000000 N
b111 ,
b111 Q
b111 ^
b10001010011010 P
b10001010011010 S
b110 #
b110 O
b110 T
b110 ]
1!
#350
0!
#375
b100010100110010000000000000000000000000 .
b100010100110010000000000000000000000000 M
b100010100110010000000000000000000000000 R
b1000 ,
b1000 Q
b1000 ^
b10001010011001 P
b10001010011001 S
b111 #
b111 O
b111 T
b111 ]
b100010100110100000000000000000000000000 -
b100010100110100000000000000000000000000 6
b100010100110100000000000000000000000000 N
1!
#400
0!
#425
b111010100001010000000000000000000000000 .
b111010100001010000000000000000000000000 M
b111010100001010000000000000000000000000 R
b1000 V
b100010100110010000000000000000000000000 -
b100010100110010000000000000000000000000 6
b100010100110010000000000000000000000000 N
b1001 ,
b1001 Q
b1001 ^
b11101010000101 P
b11101010000101 S
b1000 #
b1000 O
b1000 T
b1000 ]
1!
#450
0!
#475
b1000110000001010000000000000000000000000 .
b1000110000001010000000000000000000000000 M
b1000110000001010000000000000000000000000 R
b11 :
b1010 ,
b1010 Q
b1010 ^
b100011000000101 P
b100011000000101 S
b1001 #
b1001 O
b1001 T
b1001 ]
b111010100001010000000000000000000000000 -
b111010100001010000000000000000000000000 6
b111010100001010000000000000000000000000 N
1!
#500
0!
#525
b100 :
b1011010110001110000000000000000000000000 .
b1011010110001110000000000000000000000000 M
b1011010110001110000000000000000000000000 R
b1000110000001010000000000000000000000000 -
b1000110000001010000000000000000000000000 6
b1000110000001010000000000000000000000000 N
b1011 ,
b1011 Q
b1011 ^
b101101011000111 P
b101101011000111 S
b1010 #
b1010 O
b1010 T
b1010 ]
1!
